datahub/__init__.py
datahub/api.py
datahub/config.py
datahub/formatter.py
datahub/telematics.py
pyDatahubDriver-0.1.2.dist-info/LICENSE
pyDatahubDriver-0.1.2.dist-info/METADATA
pyDatahubDriver-0.1.2.dist-info/WHEEL
pyDatahubDriver-0.1.2.dist-info/top_level.txt
pyDatahubDriver-0.1.2.dist-info/RECORD
