Metadata-Version: 2.1
Name: pyDatahubDriver
Version: 0.1.2
Summary: KAPSARC Datahub
Home-page: UNKNOWN
Author: King Abdullah Petroleum Studies and Research Center
Author-email: anup.kumar@kapsarc.org
License: UNKNOWN
Keywords: model-data data-version modelers-data-version python jupyter ipython
Platform: UNKNOWN
Classifier: Development Status :: 2 - Pre-Alpha
Classifier: Programming Language :: Python :: 3
Classifier: Programming Language :: Python :: 3.5
Classifier: Programming Language :: Python :: 3.6
Classifier: Programming Language :: Python :: 3.7
Classifier: License :: OSI Approved :: MIT License
Classifier: Operating System :: OS Independent
Classifier: Intended Audience :: Science/Research
Classifier: Intended Audience :: Developers
Classifier: Intended Audience :: Financial and Insurance Industry
Classifier: Intended Audience :: Healthcare Industry
Requires-Dist: pandas
Requires-Dist: requests
